sliceline/__init__.py
sliceline/slicefinder.py
sliceline/validation.py
zeno_sliceline-0.0.1.dist-info/LICENSE
zeno_sliceline-0.0.1.dist-info/WHEEL
zeno_sliceline-0.0.1.dist-info/METADATA
zeno_sliceline-0.0.1.dist-info/RECORD
