Metadata-Version: 2.1
Name: zeno-sliceline
Version: 0.0.1
Summary: ✂️ Fast slice finding for Machine Learning model debugging.
Home-page: https://github.com/DataDome/sliceline
License: BSD-3-Clause
Author: Antoine de Daran
Requires-Python: >=3.7
Classifier: License :: OSI Approved :: BSD License
Classifier: Programming Language :: Python :: 3
Classifier: Programming Language :: Python :: 3.7
Classifier: Programming Language :: Python :: 3.8
Classifier: Programming Language :: Python :: 3.9
Classifier: Programming Language :: Python :: 3.10
Classifier: Programming Language :: Python :: 3.11
Requires-Dist: numpy (>=1.24.3,<2.0.0)
Requires-Dist: scikit-learn (>=1.2.2,<2.0.0)
Project-URL: Documentation, https://sliceline.readthedocs.io/en/stable/
Project-URL: Repository, https://github.com/DataDome/sliceline
